{
  "clients": {
    "akropolis": {
      "name": "Akropolis Heerlen",
      "logo": "logo/logo_header.webp",
      "googlePlaceId": "ChIJ97cJ27q9wEcRsRAe5JZUD_k",
      "social": {
        "website": "https://akropolis-heerlen.nl/",
        "instagram": "https://www.instagram.com/akropolis.restaurants?igsh=OGxpdjNxc2Noamxk",
        "facebook": "https://www.facebook.com/akropolisgeleen/"
      },
      "emailTag": "AKROPOLIS"
    },
    "bellaitalia": {
      "name": "Bella Italia Heerlen",
      "logo": "logos/bellaitalia.png",
      "googlePlaceId": "BELLA_PLACE_ID_HIER",
      "social": {
        "website": "https://bellaitalia.nl",
        "instagram": "https://instagram.com/bellaitalia",
        "facebook": "https://facebook.com/bellaitalia"
      },
      "emailTag": "BELLAITALIA"
    },
    "akropolisgeleen": {
      "name": "Akropolis Geleen",
      "logo": "logo/logo_header.webp",
      "googlePlaceId": "ChIJXXMAQj_HwEcRJoP_TyRuFOU",
      "social": {
        "website": "https://akropolis-heerlen.nl/",
        "instagram": "https://www.instagram.com/akropolis.restaurants?igsh=OGxpdjNxc2Noamxk",
        "facebook": "https://www.facebook.com/akropolisgeleen/"
      },
      "emailTag": "AKROPOLIS GELEEN"
    },
    "elfuego": {
      "name": "El Fuego Valkenburg",
      "logo": "logo/el_fuego.jpg",
      "googlePlaceId": "ChIJY6mAon3rwEcRJvp-3SDPBLg",
      "social": {
        "website": "https://www.elfuegovalkenburg.nl",
        "instagram": "https://www.instagram.com/elfuego.valkenburg?igsh=N2dhYXM0ZG5kNTIz",
        "facebook": "https://m.facebook.com/elfuego.valkenburg/"
      },
      "emailTag": "ELFUEGO"
    },
    "brazza": {
      "name": "Brazza Valkenburg",
      "logo": "logo/brazza.jpg",
      "googlePlaceId": "ChIJ0YOvPavqwEcR15l6DJs6EH4",
      "social": {
        "website": "https://www.brazzavalkenburg.nl",
        "instagram": "https://www.instagram.com/brazza.valkenburg?igsh=MTYydGwyeDJlaGpq",
        "facebook": "https://m.facebook.com/brazza.valkenburg/"
      },
      "emailTag": "BRAZZA"
    },
    "rossa": {
      "name": "La Rossa Valkenburg",
      "logo": "logo/larossa.jpg",
      "googlePlaceId": "ChIJWc6nUKnrwEcRhqup6mAjMic",
      "social": {
        "website": "https://larossavalkenburg.nl",
        "instagram": "https://www.instagram.com/brazza.valkenburg?igsh=MTYydGwyeDJlaGpq",
        "facebook": "https://www.facebook.com/61557890094002/"
      },
      "emailTag": "LAROSSA"
    },
    "wieetsjaf": {
      "name": "Dé Wieetsjaf",
      "logo": "logo/logo_wieetsjaf.svg",
      "googlePlaceId": "ChIJcSP1O6KiokYRZZC7Uo6W4CE",
      "social": {
        "website": "https://www.wieetsjaf.nl/",
        "instagram": "https://www.instagram.com/wieetsjaf/",
        "facebook": "https://www.facebook.com/Wieetsjaf/"
      },
      "emailTag": "WIEETSJAF"
    }
  },
  "_instructies": {
    "nieweKlant": "Kopieer een bestaand block, verander clientId (lowercase), naam, logo pad, googlePlaceId, social links en emailTag",
    "googlePlaceId": "Zoek op: https://developers.google.com/maps/documentation/places/web-service/place-id",
    "emailTag": "Dit verschijnt in email subject als [TAG], gebruik HOOFDLETTERS zonder spaties",
    "logo": "Upload logo naar /logos/ folder of gebruik bestaande uit /logo/ folder"
  }
}
